caketool/__init__.py
caketool/__main__.py
caketool/calibration/__init__.py
caketool/calibration/normal_norm.py
caketool/experiment/__init__.py
caketool/experiment/experiment_tracker.py
caketool/feature/__init__.py
caketool/feature/feature_encoder.py
caketool/feature/feature_generator.py
caketool/feature/feature_remover.py
caketool/feature/infinity_handler.py
caketool/metric/__init__.py
caketool/metric/classification_metric.py
caketool/metric/stability_metric.py
caketool/model/__init__.py
caketool/model/boost_tree.py
caketool/model/voting_model.py
caketool/monitor/__init__.py
caketool/monitor/adversarial_test.py
caketool/monitor/model_monitor.py
caketool/report/__init__.py
caketool/report/risk_report.py
caketool/utils/__init__.py
caketool/utils/arr_utils.py
caketool/utils/bq_utils.py
caketool/utils/lib_utils.py
caketool/utils/num_utils.py
caketool/utils/phone_utils.py
caketool/utils/str_utils.py
caketool-1.7.0.dist-info/licenses/LICENSE
caketool-1.7.0.dist-info/METADATA
caketool-1.7.0.dist-info/WHEEL
caketool-1.7.0.dist-info/entry_points.txt
caketool-1.7.0.dist-info/top_level.txt
caketool-1.7.0.dist-info/RECORD
