Metadata-Version: 2.4
Name: caketool
Version: 1.7.0
Summary: Common tools for MLOps
Author-email: Khoi Do <khoi.do@cake.vn>
License-Expression: MIT
Project-URL: Homepage, https://github.com/cake-digital-bank
Keywords: cake,ds,mlops
Classifier: Programming Language :: Python
Classifier: Programming Language :: Python :: 3
Requires-Python: >=3.7
License-File: LICENSE
Provides-Extra: dev
Requires-Dist: build; extra == "dev"
Requires-Dist: twine; extra == "dev"
Requires-Dist: pip-tools; extra == "dev"
Requires-Dist: bumpver; extra == "dev"
Requires-Dist: pytest; extra == "dev"
Dynamic: license-file
